<archimate:ArchimateDiagramModel
    xmlns:xsi="http://www.w3.org/2001/XMLSchema-instance"
    xmlns:archimate="http://www.archimatetool.com/archimate"
    name="TECH:SDS Servers"
    id="43bdd32f">
  <children
      xsi:type="archimate:DiagramModelArchimateObject"
      id="7522ec41">
    <sourceConnections
        xsi:type="archimate:DiagramModelArchimateConnection"
        id="61fa1680"
        source="7522ec41"
        target="84cbf42e">
      <archimateRelationship
          xsi:type="archimate:AggregationRelationship"
          href="AggregationRelationship_af670a93.xml#af670a93"/>
    </sourceConnections>
    <sourceConnections
        xsi:type="archimate:DiagramModelArchimateConnection"
        id="a9727a0a"
        source="7522ec41"
        target="6c56e7c5">
      <archimateRelationship
          xsi:type="archimate:AggregationRelationship"
          href="AggregationRelationship_4d8d99ab.xml#4d8d99ab"/>
    </sourceConnections>
    <sourceConnections
        xsi:type="archimate:DiagramModelArchimateConnection"
        id="ec5dfa69"
        source="7522ec41"
        target="0c72e648">
      <archimateRelationship
          xsi:type="archimate:AggregationRelationship"
          href="AggregationRelationship_d2246b45.xml#d2246b45"/>
    </sourceConnections>
    <sourceConnections
        xsi:type="archimate:DiagramModelArchimateConnection"
        id="32e236b7"
        source="7522ec41"
        target="a05867a7">
      <archimateRelationship
          xsi:type="archimate:AggregationRelationship"
          href="AggregationRelationship_91e04efb.xml#91e04efb"/>
    </sourceConnections>
    <sourceConnections
        xsi:type="archimate:DiagramModelArchimateConnection"
        id="5ee4d65c"
        source="7522ec41"
        target="fde3c265">
      <archimateRelationship
          xsi:type="archimate:AggregationRelationship"
          href="AggregationRelationship_3e38e016.xml#3e38e016"/>
    </sourceConnections>
    <sourceConnections
        xsi:type="archimate:DiagramModelArchimateConnection"
        id="c0772481"
        source="7522ec41"
        target="3b3872a5">
      <archimateRelationship
          xsi:type="archimate:AggregationRelationship"
          href="AggregationRelationship_0700a35d.xml#0700a35d"/>
    </sourceConnections>
    <sourceConnections
        xsi:type="archimate:DiagramModelArchimateConnection"
        id="91eb98d8"
        source="7522ec41"
        target="fcd3c633">
      <archimateRelationship
          xsi:type="archimate:AggregationRelationship"
          href="AggregationRelationship_11f37ea4.xml#11f37ea4"/>
    </sourceConnections>
    <sourceConnections
        xsi:type="archimate:DiagramModelArchimateConnection"
        id="f31d3279"
        source="7522ec41"
        target="40f6ff9c">
      <archimateRelationship
          xsi:type="archimate:AggregationRelationship"
          href="AggregationRelationship_04cf187c.xml#04cf187c"/>
    </sourceConnections>
    <sourceConnections
        xsi:type="archimate:DiagramModelArchimateConnection"
        id="63809962"
        source="7522ec41"
        target="40e9d934">
      <archimateRelationship
          xsi:type="archimate:AggregationRelationship"
          href="AggregationRelationship_553126cc.xml#553126cc"/>
    </sourceConnections>
    <sourceConnections
        xsi:type="archimate:DiagramModelArchimateConnection"
        id="dc3ef040"
        source="7522ec41"
        target="9ca2cec4">
      <archimateRelationship
          xsi:type="archimate:AggregationRelationship"
          href="AggregationRelationship_7b10dc34.xml#7b10dc34"/>
    </sourceConnections>
    <sourceConnections
        xsi:type="archimate:DiagramModelArchimateConnection"
        id="a9bbbc83"
        source="7522ec41"
        target="8abafa02">
      <archimateRelationship
          xsi:type="archimate:AggregationRelationship"
          href="AggregationRelationship_1cbdb53d.xml#1cbdb53d"/>
    </sourceConnections>
    <bounds
        x="12"
        y="12"
        width="841"
        height="373"/>
    <children
        xsi:type="archimate:DiagramModelArchimateObject"
        id="84cbf42e"
        targetConnections="61fa1680 06914d6b d7ab8890">
      <sourceConnections
          xsi:type="archimate:DiagramModelArchimateConnection"
          id="3fbc40dd"
          source="84cbf42e"
          target="fde3c265">
        <archimateRelationship
            xsi:type="archimate:RealizationRelationship"
            href="RealizationRelationship_02309bd8.xml#02309bd8"/>
      </sourceConnections>
      <bounds
          x="108"
          y="120"
          width="120"
          height="55"/>
      <archimateElement
          xsi:type="archimate:Device"
          href="Device_34b48cf9.xml#34b48cf9"/>
    </children>
    <children
        xsi:type="archimate:DiagramModelArchimateObject"
        id="6c56e7c5"
        targetConnections="a9727a0a 05c227f9">
      <sourceConnections
          xsi:type="archimate:DiagramModelArchimateConnection"
          id="06914d6b"
          source="6c56e7c5"
          target="84cbf42e">
        <archimateRelationship
            xsi:type="archimate:ServingRelationship"
            href="ServingRelationship_132fd2b9.xml#132fd2b9"/>
      </sourceConnections>
      <bounds
          x="12"
          y="204"
          width="120"
          height="55"/>
      <archimateElement
          xsi:type="archimate:Device"
          href="Device_4b0a700a.xml#4b0a700a"/>
    </children>
    <children
        xsi:type="archimate:DiagramModelArchimateObject"
        id="0c72e648"
        targetConnections="ec5dfa69 cac9f4f9">
      <sourceConnections
          xsi:type="archimate:DiagramModelArchimateConnection"
          id="d7ab8890"
          source="0c72e648"
          target="84cbf42e">
        <archimateRelationship
            xsi:type="archimate:ServingRelationship"
            href="ServingRelationship_d220c7dd.xml#d220c7dd"/>
      </sourceConnections>
      <bounds
          x="192"
          y="204"
          width="120"
          height="55"/>
      <archimateElement
          xsi:type="archimate:Device"
          href="Device_a6a0114e.xml#a6a0114e"/>
    </children>
    <children
        xsi:type="archimate:DiagramModelArchimateObject"
        id="a05867a7"
        targetConnections="32e236b7">
      <sourceConnections
          xsi:type="archimate:DiagramModelArchimateConnection"
          id="cac9f4f9"
          source="a05867a7"
          target="0c72e648">
        <archimateRelationship
            xsi:type="archimate:ServingRelationship"
            href="ServingRelationship_781f47b2.xml#781f47b2"/>
      </sourceConnections>
      <sourceConnections
          xsi:type="archimate:DiagramModelArchimateConnection"
          id="05c227f9"
          source="a05867a7"
          target="6c56e7c5">
        <archimateRelationship
            xsi:type="archimate:ServingRelationship"
            href="ServingRelationship_4af3d128.xml#4af3d128"/>
      </sourceConnections>
      <bounds
          x="108"
          y="288"
          width="120"
          height="55"/>
      <archimateElement
          xsi:type="archimate:Device"
          href="Device_74a8eee0.xml#74a8eee0"/>
    </children>
    <children
        xsi:type="archimate:DiagramModelArchimateObject"
        id="fde3c265"
        targetConnections="5ee4d65c 3fbc40dd">
      <bounds
          x="108"
          y="36"
          width="120"
          height="55"/>
      <archimateElement
          xsi:type="archimate:ApplicationComponent"
          href="ApplicationComponent_0853f83d.xml#0853f83d"/>
    </children>
    <children
        xsi:type="archimate:DiagramModelArchimateObject"
        id="3b3872a5"
        targetConnections="c0772481">
      <sourceConnections
          xsi:type="archimate:DiagramModelArchimateConnection"
          id="0f700926"
          source="3b3872a5"
          target="40f6ff9c">
        <archimateRelationship
            xsi:type="archimate:ServingRelationship"
            href="ServingRelationship_6bba7c73.xml#6bba7c73"/>
      </sourceConnections>
      <bounds
          x="348"
          y="204"
          width="120"
          height="55"/>
      <archimateElement
          xsi:type="archimate:Device"
          href="Device_517b0c37.xml#517b0c37"/>
    </children>
    <children
        xsi:type="archimate:DiagramModelArchimateObject"
        id="fcd3c633"
        targetConnections="91eb98d8">
      <sourceConnections
          xsi:type="archimate:DiagramModelArchimateConnection"
          id="b237cdf0"
          source="fcd3c633"
          target="40f6ff9c">
        <archimateRelationship
            xsi:type="archimate:ServingRelationship"
            href="ServingRelationship_d7b2cadb.xml#d7b2cadb"/>
      </sourceConnections>
      <bounds
          x="528"
          y="204"
          width="120"
          height="55"/>
      <archimateElement
          xsi:type="archimate:Device"
          href="Device_fa88f6f0.xml#fa88f6f0"/>
    </children>
    <children
        xsi:type="archimate:DiagramModelArchimateObject"
        id="40f6ff9c"
        targetConnections="f31d3279 0f700926 b237cdf0">
      <sourceConnections
          xsi:type="archimate:DiagramModelArchimateConnection"
          id="0f534096"
          source="40f6ff9c"
          target="40e9d934">
        <archimateRelationship
            xsi:type="archimate:RealizationRelationship"
            href="RealizationRelationship_0a7c176d.xml#0a7c176d"/>
      </sourceConnections>
      <bounds
          x="443"
          y="120"
          width="120"
          height="55"/>
      <archimateElement
          xsi:type="archimate:Device"
          href="Device_3b458f6f.xml#3b458f6f"/>
    </children>
    <children
        xsi:type="archimate:DiagramModelArchimateObject"
        id="40e9d934"
        targetConnections="63809962 0f534096">
      <bounds
          x="443"
          y="36"
          width="120"
          height="55"/>
      <archimateElement
          xsi:type="archimate:ApplicationComponent"
          href="ApplicationComponent_ebcf6a6b.xml#ebcf6a6b"/>
    </children>
    <children
        xsi:type="archimate:DiagramModelArchimateObject"
        id="9ca2cec4"
        targetConnections="dc3ef040 a66196bb">
      <bounds
          x="696"
          y="36"
          width="120"
          height="55"/>
      <archimateElement
          xsi:type="archimate:ApplicationComponent"
          href="ApplicationComponent_4dbc8de0.xml#4dbc8de0"/>
    </children>
    <children
        xsi:type="archimate:DiagramModelArchimateObject"
        id="8abafa02"
        targetConnections="a9bbbc83">
      <sourceConnections
          xsi:type="archimate:DiagramModelArchimateConnection"
          id="a66196bb"
          source="8abafa02"
          target="9ca2cec4">
        <archimateRelationship
            xsi:type="archimate:RealizationRelationship"
            href="RealizationRelationship_921947c4.xml#921947c4"/>
      </sourceConnections>
      <bounds
          x="696"
          y="120"
          width="120"
          height="55"/>
      <archimateElement
          xsi:type="archimate:Device"
          href="Device_0f0b84bc.xml#0f0b84bc"/>
    </children>
    <archimateElement
        xsi:type="archimate:Grouping"
        href="Grouping_62d2fced.xml#62d2fced"/>
  </children>
  <children
      xsi:type="archimate:DiagramModelArchimateObject"
      id="caf4c721">
    <sourceConnections
        xsi:type="archimate:DiagramModelArchimateConnection"
        id="1f598bf8"
        source="caf4c721"
        target="ec146be2">
      <archimateRelationship
          xsi:type="archimate:AggregationRelationship"
          href="AggregationRelationship_13b303f6.xml#13b303f6"/>
    </sourceConnections>
    <sourceConnections
        xsi:type="archimate:DiagramModelArchimateConnection"
        id="a00b0ff4"
        source="caf4c721"
        target="5ca52fe8">
      <archimateRelationship
          xsi:type="archimate:AggregationRelationship"
          href="AggregationRelationship_c9b3f99f.xml#c9b3f99f"/>
    </sourceConnections>
    <sourceConnections
        xsi:type="archimate:DiagramModelArchimateConnection"
        id="bfc48512"
        source="caf4c721"
        target="494c314c">
      <archimateRelationship
          xsi:type="archimate:AggregationRelationship"
          href="AggregationRelationship_bf7d8655.xml#bf7d8655"/>
    </sourceConnections>
    <sourceConnections
        xsi:type="archimate:DiagramModelArchimateConnection"
        id="098ce109"
        source="caf4c721"
        target="c1ac08db">
      <archimateRelationship
          xsi:type="archimate:AggregationRelationship"
          href="AggregationRelationship_ec3288aa.xml#ec3288aa"/>
    </sourceConnections>
    <sourceConnections
        xsi:type="archimate:DiagramModelArchimateConnection"
        id="ce8f0165"
        source="caf4c721"
        target="d3b27ccf">
      <archimateRelationship
          xsi:type="archimate:AggregationRelationship"
          href="AggregationRelationship_d78e465a.xml#d78e465a"/>
    </sourceConnections>
    <sourceConnections
        xsi:type="archimate:DiagramModelArchimateConnection"
        id="ee334637"
        source="caf4c721"
        target="7b041b92">
      <archimateRelationship
          xsi:type="archimate:AggregationRelationship"
          href="AggregationRelationship_25efbcde.xml#25efbcde"/>
    </sourceConnections>
    <sourceConnections
        xsi:type="archimate:DiagramModelArchimateConnection"
        id="b2692c03"
        source="caf4c721"
        target="538c6bc2">
      <archimateRelationship
          xsi:type="archimate:AggregationRelationship"
          href="AggregationRelationship_e18dd808.xml#e18dd808"/>
    </sourceConnections>
    <sourceConnections
        xsi:type="archimate:DiagramModelArchimateConnection"
        id="50b8cc36"
        source="caf4c721"
        target="5f239115">
      <archimateRelationship
          xsi:type="archimate:AggregationRelationship"
          href="AggregationRelationship_597fd2dd.xml#597fd2dd"/>
    </sourceConnections>
    <sourceConnections
        xsi:type="archimate:DiagramModelArchimateConnection"
        id="b6a08209"
        source="caf4c721"
        target="effbb54d">
      <archimateRelationship
          xsi:type="archimate:AggregationRelationship"
          href="AggregationRelationship_5438c4c3.xml#5438c4c3"/>
    </sourceConnections>
    <sourceConnections
        xsi:type="archimate:DiagramModelArchimateConnection"
        id="29f3e6ce"
        source="caf4c721"
        target="68493b64">
      <archimateRelationship
          xsi:type="archimate:AggregationRelationship"
          href="AggregationRelationship_06bdb7e0.xml#06bdb7e0"/>
    </sourceConnections>
    <sourceConnections
        xsi:type="archimate:DiagramModelArchimateConnection"
        id="72ff3b9f"
        source="caf4c721"
        target="1a31ee54">
      <archimateRelationship
          xsi:type="archimate:AggregationRelationship"
          href="AggregationRelationship_cd571a6c.xml#cd571a6c"/>
    </sourceConnections>
    <bounds
        x="12"
        y="396"
        width="841"
        height="601"/>
    <children
        xsi:type="archimate:DiagramModelArchimateObject"
        id="ec146be2"
        targetConnections="1f598bf8 69b6a1be 50fad7b3 ae95f4cf">
      <sourceConnections
          xsi:type="archimate:DiagramModelArchimateConnection"
          id="f37b3d46"
          source="ec146be2"
          target="5ca52fe8">
        <archimateRelationship
            xsi:type="archimate:RealizationRelationship"
            href="RealizationRelationship_f6bfe464.xml#f6bfe464"/>
      </sourceConnections>
      <bounds
          x="156"
          y="120"
          width="120"
          height="55"/>
      <archimateElement
          xsi:type="archimate:Device"
          href="Device_f1828400.xml#f1828400"/>
    </children>
    <children
        xsi:type="archimate:DiagramModelArchimateObject"
        id="5ca52fe8"
        targetConnections="a00b0ff4 f37b3d46">
      <bounds
          x="156"
          y="36"
          width="120"
          height="55"/>
      <archimateElement
          xsi:type="archimate:ApplicationComponent"
          href="ApplicationComponent_00c7e812.xml#00c7e812"/>
    </children>
    <children
        xsi:type="archimate:DiagramModelArchimateObject"
        id="494c314c"
        targetConnections="bfc48512">
      <sourceConnections
          xsi:type="archimate:DiagramModelArchimateConnection"
          id="69b6a1be"
          source="494c314c"
          target="ec146be2">
        <archimateRelationship
            xsi:type="archimate:ServingRelationship"
            href="ServingRelationship_3e735bef.xml#3e735bef"/>
      </sourceConnections>
      <bounds
          x="24"
          y="204"
          width="120"
          height="55"/>
      <archimateElement
          xsi:type="archimate:Device"
          href="Device_587ceb81.xml#587ceb81"/>
    </children>
    <children
        xsi:type="archimate:DiagramModelArchimateObject"
        id="c1ac08db"
        targetConnections="098ce109">
      <sourceConnections
          xsi:type="archimate:DiagramModelArchimateConnection"
          id="50fad7b3"
          source="c1ac08db"
          target="ec146be2">
        <archimateRelationship
            xsi:type="archimate:ServingRelationship"
            href="ServingRelationship_ff6bd11f.xml#ff6bd11f"/>
      </sourceConnections>
      <bounds
          x="156"
          y="204"
          width="120"
          height="55"/>
      <archimateElement
          xsi:type="archimate:Device"
          href="Device_653403e2.xml#653403e2"/>
    </children>
    <children
        xsi:type="archimate:DiagramModelArchimateObject"
        id="d3b27ccf"
        targetConnections="ce8f0165">
      <sourceConnections
          xsi:type="archimate:DiagramModelArchimateConnection"
          id="ae95f4cf"
          source="d3b27ccf"
          target="ec146be2">
        <archimateRelationship
            xsi:type="archimate:ServingRelationship"
            href="ServingRelationship_87db214c.xml#87db214c"/>
      </sourceConnections>
      <bounds
          x="288"
          y="204"
          width="120"
          height="55"/>
      <archimateElement
          xsi:type="archimate:Device"
          href="Device_3ffdcb9d.xml#3ffdcb9d"/>
    </children>
    <children
        xsi:type="archimate:DiagramModelArchimateObject"
        id="7b041b92"
        targetConnections="ee334637 23c8086c">
      <sourceConnections
          xsi:type="archimate:DiagramModelArchimateConnection"
          id="d49feb22"
          source="7b041b92"
          target="5f239115">
        <archimateRelationship
            xsi:type="archimate:RealizationRelationship"
            href="RealizationRelationship_07c831f0.xml#07c831f0"/>
      </sourceConnections>
      <bounds
          x="444"
          y="120"
          width="120"
          height="55"/>
      <archimateElement
          xsi:type="archimate:Device"
          href="Device_4cb19b1f.xml#4cb19b1f"/>
    </children>
    <children
        xsi:type="archimate:DiagramModelArchimateObject"
        id="538c6bc2"
        targetConnections="b2692c03">
      <sourceConnections
          xsi:type="archimate:DiagramModelArchimateConnection"
          id="23c8086c"
          source="538c6bc2"
          target="7b041b92">
        <archimateRelationship
            xsi:type="archimate:ServingRelationship"
            href="ServingRelationship_7d8d92a1.xml#7d8d92a1"/>
      </sourceConnections>
      <bounds
          x="444"
          y="204"
          width="120"
          height="55"/>
      <archimateElement
          xsi:type="archimate:Device"
          href="Device_49bb4b2d.xml#49bb4b2d"/>
    </children>
    <children
        xsi:type="archimate:DiagramModelArchimateObject"
        id="5f239115"
        targetConnections="50b8cc36 d49feb22">
      <bounds
          x="444"
          y="36"
          width="120"
          height="55"/>
      <archimateElement
          xsi:type="archimate:ApplicationComponent"
          href="ApplicationComponent_ab54ad99.xml#ab54ad99"/>
    </children>
    <children
        xsi:type="archimate:DiagramModelArchimateObject"
        id="effbb54d"
        targetConnections="b6a08209">
      <sourceConnections
          xsi:type="archimate:DiagramModelArchimateConnection"
          id="0d1ae55b"
          source="effbb54d"
          target="68493b64">
        <archimateRelationship
            xsi:type="archimate:ServingRelationship"
            href="ServingRelationship_3f1aabe6.xml#3f1aabe6"/>
      </sourceConnections>
      <bounds
          x="624"
          y="204"
          width="120"
          height="55"/>
      <archimateElement
          xsi:type="archimate:Device"
          href="Device_d393b03f.xml#d393b03f"/>
    </children>
    <children
        xsi:type="archimate:DiagramModelArchimateObject"
        id="68493b64"
        targetConnections="29f3e6ce 0d1ae55b">
      <sourceConnections
          xsi:type="archimate:DiagramModelArchimateConnection"
          id="ba705f12"
          source="68493b64"
          target="1a31ee54">
        <archimateRelationship
            xsi:type="archimate:RealizationRelationship"
            href="RealizationRelationship_2972a3f8.xml#2972a3f8"/>
      </sourceConnections>
      <bounds
          x="624"
          y="120"
          width="120"
          height="55"/>
      <archimateElement
          xsi:type="archimate:Device"
          href="Device_bec6b1d7.xml#bec6b1d7"/>
    </children>
    <children
        xsi:type="archimate:DiagramModelArchimateObject"
        id="1a31ee54"
        targetConnections="72ff3b9f ba705f12">
      <bounds
          x="624"
          y="36"
          width="120"
          height="55"/>
      <archimateElement
          xsi:type="archimate:ApplicationComponent"
          href="ApplicationComponent_9d96e242.xml#9d96e242"/>
    </children>
    <archimateElement
        xsi:type="archimate:Grouping"
        href="Grouping_6310018b.xml#6310018b"/>
  </children>
</archimate:ArchimateDiagramModel>
